ffxiv_crafting-6.5.1.dist-info/METADATA
ffxiv_crafting-6.5.1.dist-info/WHEEL
ffxiv_crafting-6.5.1.dist-info/license_files/LICENSE
ffxiv_crafting/__init__.py
ffxiv_crafting/ffxiv_crafting.cp311-win_amd64.pyd
ffxiv_crafting-6.5.1.dist-info/RECORD
