Metadata-Version: 2.3
Name: ffxiv-crafting
Version: 6.5.1
Classifier: Programming Language :: Rust
Classifier: Programming Language :: Python :: Implementation :: CPython
Classifier: Programming Language :: Python :: Implementation :: PyPy
License-File: LICENSE
Summary: A crafting simulator of FFXIV.
Keywords: ff14,ffxiv
Author: Tnze <cjd001113@outlook.com>
Author-email: Tnze <cjd001113@outlook.com>
License: MIT
Requires-Python: >=3.8
Project-URL: Source Code, https://github.com/Tnze/ffxiv-crafting
